bits/__init__.py
bits/mhl/__init__.py
bits/mhl/types.py
bits_mhl-1.21.6.dist-info/LICENSE.txt
bits_mhl-1.21.6.dist-info/METADATA
bits_mhl-1.21.6.dist-info/WHEEL
bits_mhl-1.21.6.dist-info/RECORD
