Metadata-Version: 2.3
Name: bits-mhl
Version: 1.21.6
Summary: BITS MHL
License: BSD-3-Clause
Keywords: bits,mhl
Author: DevNull
Author-email: <devnull@broadinstitute.org>
Requires-Python: >=3.9
Classifier: License :: OSI Approved :: BSD License
Classifier: Programming Language :: Python :: 3
Classifier: Programming Language :: Python :: 3.9
Classifier: Programming Language :: Python :: 3.10
Classifier: Programming Language :: Python :: 3.11
Classifier: Programming Language :: Python :: 3.12
Classifier: Programming Language :: Python :: 3.13
Requires-Dist: netaddr (>=1.3.0,<2.0.0)
Project-URL: Homepage, https://github.com/broadinstitute/bits-mhl.git
Project-URL: Repository, https://github.com/broadinstitute/bits-mhl.git
